BSeries/__init__.py
BSeries/bs.py
BSeries/test_trees.py
BSeries/trees.py
BSeries/util.py
BSeries-0.1.dist-info/LICENSE.txt
BSeries-0.1.dist-info/METADATA
BSeries-0.1.dist-info/WHEEL
BSeries-0.1.dist-info/top_level.txt
BSeries-0.1.dist-info/RECORD
